[
    {
        "type": "message",
        "user": "U03SSL0FM",
        "text": "<https:\/\/toggl.com\/developer-methods-infographic>",
        "attachments": [
            {
                "fallback": "A 1200x630px image",
                "image_url": "https:\/\/toggl.com\/images\/share-img\/fb-share-img.jpg",
                "from_url": "https:\/\/toggl.com\/developer-methods-infographic",
                "image_width": 476,
                "image_height": 250,
                "image_bytes": 500865,
                "id": 1
            }
        ],
        "ts": "1454672322.000005"
    },
    {
        "user": "U0LE0FHK9",
        "type": "message",
        "subtype": "channel_join",
        "text": "<@U0LE0FHK9|cmumeche> has joined the channel",
        "ts": "1454705975.000007"
    }
]