[
    {
        "bot_id": "B0429JVR5",
        "attachments": [
            {
                "fallback": "<https:\/\/twitter.com\/EmberLondon|@EmberLondon>: \u201cOur Journey with the Tomster\u201d a talk by <https:\/\/twitter.com\/deepanice|@deepanice> and friends from our April meetup.\n\n<https:\/\/vimeo.com\/124930055>",
                "author_name": "Ember london",
                "author_link": "https:\/\/twitter.com\/EmberLondon\/status\/588252940818866176",
                "author_icon": "https:\/\/pbs.twimg.com\/profile_images\/490089444473835522\/AbHfjBqC_normal.jpeg",
                "author_subname": "@EmberLondon",
                "pretext": "<https:\/\/twitter.com\/EmberLondon\/status\/588252940818866176>",
                "text": "\u201cOur Journey with the Tomster\u201d a talk by <https:\/\/twitter.com\/deepanice|@deepanice> and friends from our April meetup.\n\n<https:\/\/vimeo.com\/124930055>",
                "service_name": "twitter",
                "service_url": "https:\/\/twitter.com\/",
                "id": 1,
                "footer": "Twitter",
                "footer_icon": "https:\/\/a.slack-edge.com\/6e067\/img\/services\/twitter_pixel_snapped_32.png"
            }
        ],
        "type": "message",
        "subtype": "bot_message",
        "ts": "1429085405.000005"
    },
    {
        "bot_id": "B0429JVR5",
        "attachments": [
            {
                "fallback": "<https:\/\/twitter.com\/EmberLondon|@EmberLondon>: \u201cRoutes Manuva - Unpacking Ember\u2019s routes and the router\u201d a talk by <https:\/\/twitter.com\/TheGameOf79|@TheGameOf79> from our April meetup.\n\n<https:\/\/vimeo.com\/124906883>",
                "author_name": "Ember london",
                "author_link": "https:\/\/twitter.com\/EmberLondon\/status\/588253644123983872",
                "author_icon": "https:\/\/pbs.twimg.com\/profile_images\/490089444473835522\/AbHfjBqC_normal.jpeg",
                "author_subname": "@EmberLondon",
                "pretext": "<https:\/\/twitter.com\/EmberLondon\/status\/588253644123983872>",
                "text": "\u201cRoutes Manuva - Unpacking Ember\u2019s routes and the router\u201d a talk by <https:\/\/twitter.com\/TheGameOf79|@TheGameOf79> from our April meetup.\n\n<https:\/\/vimeo.com\/124906883>",
                "service_name": "twitter",
                "service_url": "https:\/\/twitter.com\/",
                "id": 1,
                "footer": "Twitter",
                "footer_icon": "https:\/\/a.slack-edge.com\/6e067\/img\/services\/twitter_pixel_snapped_32.png"
            }
        ],
        "type": "message",
        "subtype": "bot_message",
        "ts": "1429085572.000006"
    },
    {
        "bot_id": "B0429JVR5",
        "attachments": [
            {
                "fallback": "<https:\/\/twitter.com\/EmberLondon|@EmberLondon>: \u201cHamsters on Fire\u201d a talk by <https:\/\/twitter.com\/codepreneurr|@codepreneurr> from our April meetup.\n\n<https:\/\/vimeo.com\/124906884>",
                "author_name": "Ember london",
                "author_link": "https:\/\/twitter.com\/EmberLondon\/status\/588253794913427456",
                "author_icon": "https:\/\/pbs.twimg.com\/profile_images\/490089444473835522\/AbHfjBqC_normal.jpeg",
                "author_subname": "@EmberLondon",
                "pretext": "<https:\/\/twitter.com\/EmberLondon\/status\/588253794913427456>",
                "text": "\u201cHamsters on Fire\u201d a talk by <https:\/\/twitter.com\/codepreneurr|@codepreneurr> from our April meetup.\n\n<https:\/\/vimeo.com\/124906884>",
                "service_name": "twitter",
                "service_url": "https:\/\/twitter.com\/",
                "id": 1,
                "footer": "Twitter",
                "footer_icon": "https:\/\/a.slack-edge.com\/6e067\/img\/services\/twitter_pixel_snapped_32.png"
            }
        ],
        "type": "message",
        "subtype": "bot_message",
        "ts": "1429085608.000007"
    }
]