[
    {
        "type": "message",
        "user": "U043AB2QT",
        "text": "So, I'm in the process of upgrading from 1.13.12 to 2.4.2 and I'm trying to fix our tests....I'm seeing one test timing out....It looks like there is a promise or two that is not resolving and therefore the test is not continuing....\n\nOnly thing is, in the ember inspector, there is bugger all info about the promises in questions. The image below shows what I can see.\n\nHow on earth do I work out where `Unknown Promise` comes from?",
        "ts": "1458656452.000002"
    },
    {
        "type": "message",
        "subtype": "file_share",
        "text": "<@U043AB2QT|aaron> uploaded a file: <https:\/\/emberlondon.slack.com\/files\/aaron\/F0UHJAXDY\/pasted_image_at_2016_03_22_02_20_pm.png|Pasted image at 2016-03-22, 2:20 PM>",
        "file": {
            "id": "F0UHJAXDY",
            "created": 1458656456,
            "timestamp": 1458656456,
            "name": "Pasted image at 2016_03_22 02_20 PM.png",
            "title": "Pasted image at 2016-03-22, 2:20 PM",
            "mimetype": "image\/png",
            "filetype": "png",
            "pretty_type": "PNG",
            "user": "U043AB2QT",
            "editable": false,
            "size": 58681,
            "mode": "hosted",
            "is_external": false,
            "external_type": "",
            "is_public": true,
            "public_url_shared": false,
            "display_as_bot": false,
            "username": "",
            "url_private": "https:\/\/files.slack.com\/files-pri\/T03SSL0FF-F0UHJAXDY\/pasted_image_at_2016_03_22_02_20_pm.png?t=xoxe-3910680525-115741181265-116496169492-28d023e02c",
            "url_private_download": "https:\/\/files.slack.com\/files-pri\/T03SSL0FF-F0UHJAXDY\/download\/pasted_image_at_2016_03_22_02_20_pm.png?t=xoxe-3910680525-115741181265-116496169492-28d023e02c",
            "thumb_64": "https:\/\/files.slack.com\/files-tmb\/T03SSL0FF-F0UHJAXDY-f5ff022979\/pasted_image_at_2016_03_22_02_20_pm_64.png?t=xoxe-3910680525-115741181265-116496169492-28d023e02c",
            "thumb_80": "https:\/\/files.slack.com\/files-tmb\/T03SSL0FF-F0UHJAXDY-f5ff022979\/pasted_image_at_2016_03_22_02_20_pm_80.png?t=xoxe-3910680525-115741181265-116496169492-28d023e02c",
            "thumb_360": "https:\/\/files.slack.com\/files-tmb\/T03SSL0FF-F0UHJAXDY-f5ff022979\/pasted_image_at_2016_03_22_02_20_pm_360.png?t=xoxe-3910680525-115741181265-116496169492-28d023e02c",
            "thumb_360_w": 360,
            "thumb_360_h": 25,
            "thumb_480": "https:\/\/files.slack.com\/files-tmb\/T03SSL0FF-F0UHJAXDY-f5ff022979\/pasted_image_at_2016_03_22_02_20_pm_480.png?t=xoxe-3910680525-115741181265-116496169492-28d023e02c",
            "thumb_480_w": 480,
            "thumb_480_h": 33,
            "thumb_160": "https:\/\/files.slack.com\/files-tmb\/T03SSL0FF-F0UHJAXDY-f5ff022979\/pasted_image_at_2016_03_22_02_20_pm_160.png?t=xoxe-3910680525-115741181265-116496169492-28d023e02c",
            "thumb_720": "https:\/\/files.slack.com\/files-tmb\/T03SSL0FF-F0UHJAXDY-f5ff022979\/pasted_image_at_2016_03_22_02_20_pm_720.png?t=xoxe-3910680525-115741181265-116496169492-28d023e02c",
            "thumb_720_w": 720,
            "thumb_720_h": 50,
            "thumb_960": "https:\/\/files.slack.com\/files-tmb\/T03SSL0FF-F0UHJAXDY-f5ff022979\/pasted_image_at_2016_03_22_02_20_pm_960.png?t=xoxe-3910680525-115741181265-116496169492-28d023e02c",
            "thumb_960_w": 960,
            "thumb_960_h": 66,
            "thumb_1024": "https:\/\/files.slack.com\/files-tmb\/T03SSL0FF-F0UHJAXDY-f5ff022979\/pasted_image_at_2016_03_22_02_20_pm_1024.png?t=xoxe-3910680525-115741181265-116496169492-28d023e02c",
            "thumb_1024_w": 1024,
            "thumb_1024_h": 70,
            "image_exif_rotation": 1,
            "original_w": 3110,
            "original_h": 214,
            "permalink": "https:\/\/emberlondon.slack.com\/files\/aaron\/F0UHJAXDY\/pasted_image_at_2016_03_22_02_20_pm.png",
            "permalink_public": "https:\/\/slack-files.com\/T03SSL0FF-F0UHJAXDY-e0b20fc807",
            "channels": [
                "C04UJ4W1M"
            ],
            "groups": [],
            "ims": [],
            "comments_count": 0
        },
        "user": "U043AB2QT",
        "upload": true,
        "display_as_bot": false,
        "username": "<@U043AB2QT|aaron>",
        "bot_id": null,
        "ts": "1458656459.000003"
    },
    {
        "type": "message",
        "user": "U043AB2QT",
        "text": "Anyone have any advice on how you'd trace this sort of thing to find out why it remains unresolved?",
        "ts": "1458656473.000004"
    },
    {
        "type": "message",
        "user": "U05485UQL",
        "text": "shot in the dark but, if it\u2019s a promise in your own code, labelling them may help",
        "ts": "1458656676.000005"
    },
    {
        "type": "message",
        "user": "U05485UQL",
        "text": "I think all of RSVP\u2019s promise-creating function take a label that will appear on the inspector",
        "ts": "1458656698.000006"
    },
    {
        "type": "message",
        "user": "U043AB2QT",
        "text": "I can't see how it could be a promise from our own code.",
        "ts": "1458657145.000007"
    },
    {
        "type": "message",
        "user": "U05485UQL",
        "text": "darn :confused:",
        "edited": {
            "user": "U05485UQL",
            "ts": "1458657275.000000"
        },
        "ts": "1458657272.000008"
    }
]