[
    {
        "type": "message",
        "user": "U05485UQL",
        "text": "I inject a service into a controller. I want the service to be shut down when exiting the controller. What should I do?",
        "ts": "1469442411.000002"
    },
    {
        "type": "message",
        "user": "U05485UQL",
        "text": "I gather I either do it manually from the controller\u2019s `willDestroy` or the service should do it on its own `willDestroy`, which hopefully is called by the default implementation of `Controller#willDestroy`. Is that correct?",
        "edited": {
            "user": "U05485UQL",
            "ts": "1469442550.000000"
        },
        "ts": "1469442542.000003"
    },
    {
        "type": "message",
        "user": "U0B47NPJ9",
        "text": "controllers are singletons so they won't be destroyed until the app is destroyed - is that the behaviour you're trying to hook into?",
        "ts": "1469442738.000005"
    },
    {
        "type": "message",
        "user": "U05485UQL",
        "text": "hm, I thought they were singletons in 1.x, but stopped being in 2.x?",
        "ts": "1469442783.000006"
    },
    {
        "type": "message",
        "user": "U05485UQL",
        "text": "I may have misunderstood that part",
        "ts": "1469442851.000007"
    },
    {
        "type": "message",
        "user": "U0B47NPJ9",
        "text": "they are still singletons, I believe routable-components will get rid of that. If you want to shut down the service when exiting a screen you probably want to use the associated route's `deactivate` hook to call a method on the controller\/service",
        "ts": "1469442887.000008"
    },
    {
        "type": "message",
        "user": "U05485UQL",
        "text": "right. OK, will try that. Thanks!",
        "ts": "1469442956.000009"
    }
]